{
  "image_size": {
    "width": 1024,
    "height": 768
  },
  "wall_thickness": 6,
  "rooms": [
    {
      "id": "r0",
      "polygon": [
        [
          964,
          60
        ],
        [
          964,
          708
        ],
        [
          640,
          708
        ],
        [
          640,
          60
        ]
      ],
      "bbox": {
        "x_min": 640,
        "y_min": 60,
        "x_max": 964,
        "y_max": 708
      },
      "area": 209952.0,
      "centroid": [
        802.0,
        384.0
      ]
    },
    {
      "id": "r1",
      "polygon": [
        [
          640,
          60
        ],
        [
          640,
          385
        ],
        [
          60,
          385
        ],
        [
          60,
          60
        ]
      ],
      "bbox": {
        "x_min": 60,
        "y_min": 60,
        "x_max": 640,
        "y_max": 385
      },
      "area": 188500.0,
      "centroid": [
        350.0,
        222.5
      ]
    },
    {
      "id": "r2",
      "polygon": [
        [
          640,
          385
        ],
        [
          640,
          708
        ],
        [
          60,
          708
        ],
        [
          60,
          385
        ]
      ],
      "bbox": {
        "x_min": 60,
        "y_min": 385,
        "x_max": 640,
        "y_max": 708
      },
      "area": 187340.0,
      "centroid": [
        350.0,
        546.5
      ]
    }
  ],
  "walls": [
    {
      "id": "w0",
      "type": "exterior",
      "start": {
        "x": 60,
        "y": 60
      },
      "end": {
        "x": 964,
        "y": 60
      },
      "length": 904.0
    },
    {
      "id": "w1",
      "type": "exterior",
      "start": {
        "x": 964,
        "y": 60
      },
      "end": {
        "x": 964,
        "y": 708
      },
      "length": 648.0
    },
    {
      "id": "w2",
      "type": "exterior",
      "start": {
        "x": 60,
        "y": 708
      },
      "end": {
        "x": 964,
        "y": 708
      },
      "length": 904.0
    },
    {
      "id": "w3",
      "type": "exterior",
      "start": {
        "x": 60,
        "y": 60
      },
      "end": {
        "x": 60,
        "y": 708
      },
      "length": 648.0
    },
    {
      "id": "w4",
      "type": "interior",
      "start": {
        "x": 640,
        "y": 60
      },
      "end": {
        "x": 640,
        "y": 708
      },
      "length": 648.0
    },
    {
      "id": "w5",
      "type": "interior",
      "start": {
        "x": 60,
        "y": 385
      },
      "end": {
        "x": 640,
        "y": 385
      },
      "length": 580.0
    }
  ],
  "doors": [
    {
      "id": "d0",
      "wall_id": "w0",
      "type": "exterior",
      "start": {
        "x": 414,
        "y": 60
      },
      "end": {
        "x": 474,
        "y": 60
      },
      "width": 60,
      "hinge": {
        "x": 414,
        "y": 60
      },
      "swing_to": {
        "x": 414,
        "y": 120
      }
    },
    {
      "id": "d1",
      "wall_id": "w4",
      "type": "interior",
      "start": {
        "x": 640,
        "y": 397
      },
      "end": {
        "x": 640,
        "y": 457
      },
      "width": 60,
      "hinge": {
        "x": 640,
        "y": 457
      },
      "swing_to": {
        "x": 700,
        "y": 457
      }
    },
    {
      "id": "d2",
      "wall_id": "w5",
      "type": "interior",
      "start": {
        "x": 278,
        "y": 385
      },
      "end": {
        "x": 338,
        "y": 385
      },
      "width": 60,
      "hinge": {
        "x": 278,
        "y": 385
      },
      "swing_to": {
        "x": 278,
        "y": 445
      }
    }
  ]
}